aind_log_utils/__init__.py
aind_log_utils/log.py
aind_log_utils-0.2.4.dist-info/LICENSE
aind_log_utils-0.2.4.dist-info/METADATA
aind_log_utils-0.2.4.dist-info/WHEEL
aind_log_utils-0.2.4.dist-info/top_level.txt
aind_log_utils-0.2.4.dist-info/RECORD
